{
  "gitSyncId": "69e488cc5d9029067df64fd2_d7683ffb-7b76-4885-87ce-6b7cd3ce8a3c",
  "id": "Registrazione_qry_crea_utente_db",
  "pluginId": "postgres-plugin",
  "pluginType": "DB",
  "unpublishedAction": {
    "actionConfiguration": {
      "body": "INSERT INTO utenti (\n  id, nome, email, ruolo, azienda_id, attivo, created_at\n)\nVALUES (\n  '{{appsmith.store.nuovo_user_id}}',\n  '{{inp_nome.text}}',\n  '{{inp_email.text}}',\n  'ceo',\n  '{{appsmith.store.nuova_azienda_id}}',\n  true,\n  NOW()\n);",
      "encodeParamsToggle": true,
      "paginationType": "NONE",
      "pluginSpecifiedTemplates": [
        {
          "value": true
        }
      ],
      "timeoutInMillisecond": 10000
    },
    "confirmBeforeExecute": false,
    "datasource": {
      "id": "Database CC",
      "isAutoGenerated": false,
      "name": "Database CC",
      "pluginId": "postgres-plugin"
    },
    "dynamicBindingPathList": [
      {
        "key": "body"
      }
    ],
    "name": "qry_crea_utente_db",
    "pageId": "Registrazione",
    "runBehaviour": "MANUAL",
    "userSetOnLoad": false
  }
}